{
  "$schema": "https://beta.frontmatter.codes/frontmatter.schema.json",
  "frontMatter.framework.id": "other",
  "fontMatter.content.fmHighlight": true,
  "frontMatter.content.autoUpdateDate": true,
  "frontMatter.content.defaultFileType": "md",
  "frontMatter.taxonomy.tags": [
    "IP",
    "copyright",
    "documentation",
    "license",
    "readme",
    "support"
  ],
  "frontMatter.taxonomy.categories": [],
  "frontMatter.content.pageFolders": [
    {
      "$schema": "https://beta.frontmatter.codes/config/content.pagefolders.schema.json",
      "title": "docs",
      "path": "[[workspace]]/docs"
    }
  ]
}